yotta/__init__.py
yotta/tasks/__init__.py
yotta/tasks/finetune.py
yotta_labs-0.0.2.dist-info/LICENSE
yotta_labs-0.0.2.dist-info/METADATA
yotta_labs-0.0.2.dist-info/WHEEL
yotta_labs-0.0.2.dist-info/top_level.txt
yotta_labs-0.0.2.dist-info/RECORD
