Metadata-Version: 2.1
Name: yotta-labs
Version: 0.0.2
Summary: UNKNOWN
Home-page: UNKNOWN
License: UNKNOWN
Platform: UNKNOWN
Classifier: License :: OSI Approved :: Apache Software License
Classifier: Programming Language :: Python :: 3.8
Classifier: Programming Language :: Python :: 3.9
Classifier: Programming Language :: Python :: 3.10
Requires-Python: >=3.8
License-File: LICENSE
Requires-Dist: transformers (>=4.42.0)
Requires-Dist: datasets
Requires-Dist: accelerate (<1.0.0,>=0.33)
Requires-Dist: typing (<4.0.0,>=3.6.4) ; python_version < "3.5"
